LICENSE
README.md
setup.py
Jdatabase/__init__.py
Jdatabase/dataclassDEPC.py
Jdatabase/jdatabase.py
Jdatabase/logger.py
Jdatabase/processors.py
Jdatabase.egg-info/PKG-INFO
Jdatabase.egg-info/SOURCES.txt
Jdatabase.egg-info/dependency_links.txt
Jdatabase.egg-info/requires.txt
Jdatabase.egg-info/top_level.txt
jdatabase/__init__.py
jdatabase/jdatabase.py
jdatabase.egg-info/PKG-INFO
jdatabase.egg-info/SOURCES.txt
jdatabase.egg-info/dependency_links.txt
jdatabase.egg-info/requires.txt
jdatabase.egg-info/top_level.txt