Metadata-Version: 2.1
Name: Jdatabase
Version: 2.0.0a3
Summary: Jdatabase Python package. Designed for ease of database control and interaction within Python. The Jdatabase package supports MySQL and PostgreSQL database systems.
Home-page: https://github.com/JoshWidrick/jdb
Author: Joshua Widrick
Author-email: joshua.widrick@gmail.com
License: MIT
Platform: UNKNOWN
License-File: LICENSE
